{
  "next_period": "2026206",
  "based_on_period": "2026205",
  "recommendation": {
    "normal_numbers": [
      7,
      13,
      15,
      21,
      29,
      31
    ],
    "special_numbers": [
      37,
      47,
      35,
      43,
      49,
      41
    ],
    "primary_special_zodiac": "馬"
  },
  "recommended_normal": [
    7,
    13,
    15,
    21,
    29,
    31
  ],
  "recommended_special_top5": [
    37,
    47,
    35,
    43,
    49,
    41
  ],
  "primary_special": 37,
  "primary_special_zodiac": "馬",
  "combo_attributes": {
    "odd_even": "奇7偶0",
    "big_small": "大3小4",
    "sum": 153
  },
  "top_scores": [
    [
      37,
      899.4300000000001,
      "馬",
      "土",
      "蓝"
    ],
    [
      47,
      899.23,
      "猴",
      "木",
      "蓝"
    ],
    [
      35,
      899.15,
      "猴",
      "金",
      "红"
    ],
    [
      43,
      899.0699999999999,
      "鼠",
      "金",
      "绿"
    ],
    [
      49,
      898.91,
      "馬",
      "火",
      "绿"
    ],
    [
      41,
      898.69,
      "虎",
      "火",
      "蓝"
    ],
    [
      7,
      874.83,
      "鼠",
      "土",
      "红"
    ],
    [
      13,
      874.5699999999999,
      "馬",
      "金",
      "红"
    ],
    [
      15,
      874.55,
      "龍",
      "水",
      "蓝"
    ],
    [
      21,
      874.49,
      "狗",
      "土",
      "绿"
    ],
    [
      31,
      874.49,
      "鼠",
      "水",
      "蓝"
    ],
    [
      29,
      874.21,
      "虎",
      "土",
      "红"
    ],
    [
      9,
      858.91,
      "狗",
      "木",
      "蓝"
    ],
    [
      23,
      858.77,
      "猴",
      "水",
      "红"
    ],
    [
      45,
      849.25,
      "狗",
      "水",
      "红"
    ],
    [
      44,
      839.36,
      "豬",
      "水",
      "绿"
    ],
    [
      40,
      839.3,
      "兔",
      "火",
      "红"
    ],
    [
      32,
      839.28,
      "豬",
      "火",
      "绿"
    ],
    [
      38,
      839.22,
      "蛇",
      "木",
      "绿"
    ],
    [
      46,
      839.14,
      "雞",
      "木",
      "红"
    ]
  ]
}